setup.py
distributions/Binomialdistribution.py
distributions/Gaussiandistribution.py
distributions/Generaldistribution.py
distributions/__init__.py
guass_binomial_probability.egg-info/PKG-INFO
guass_binomial_probability.egg-info/SOURCES.txt
guass_binomial_probability.egg-info/dependency_links.txt
guass_binomial_probability.egg-info/not-zip-safe
guass_binomial_probability.egg-info/top_level.txt