Metadata-Version: 1.0
Name: guass-binomial-probability
Version: 0.1
Summary: Gaussian and Binomial distributions
Home-page: UNKNOWN
Author: Jeremiah Binyiako
Author-email: UNKNOWN
License: UNKNOWN
Platform: UNKNOWN
